SqrtS/__init__.py
SqrtS/AdvancedWidgets/Sidebar.py
SqrtS/AdvancedWidgets/VerticalSidebar.py
SqrtS/AdvancedWidgets/__init__.py
SqrtS/Animation/Animation.py
SqrtS/Animation/DynamicEffects.py
SqrtS/Animation/LoopAnimation.py
SqrtS/Animation/Vector.py
SqrtS/Animation/VectorMove.py
SqrtS/Animation/__init__.py
SqrtS/Core/AnimationSystem.py
SqrtS/Core/App.py
SqrtS/Core/SystemStray.py
SqrtS/Core/TaskSystem.py
SqrtS/Core/__init__.py
SqrtS/Core/core.py
SqrtS/Core/event_process.py
SqrtS/Core/paging.py
SqrtS/Draw/__init__.py
SqrtS/Draw/circle.py
SqrtS/Draw/lines.py
SqrtS/Draw/rect.py
SqrtS/Errors/__init__.py
SqrtS/Errors/animation_err.py
SqrtS/Errors/core_error.py
SqrtS/Errors/widgets_error.py
SqrtS/Expand/DraggingBoard.py
SqrtS/Expand/GIFPlayer.py
SqrtS/Expand/GlobalKeyBoard.py
SqrtS/Expand/WindowBorder.py
SqrtS/Expand/WindowMove.py
SqrtS/Expand/WindowTransparency.py
SqrtS/Expand/__init__.py
SqrtS/Layouts/FloatingLayout.py
SqrtS/Layouts/Layout.py
SqrtS/Layouts/LinearLayout.py
SqrtS/Layouts/__init__.py
SqrtS/Widgets/Audio.py
SqrtS/Widgets/Button.py
SqrtS/Widgets/Canvas.py
SqrtS/Widgets/FileDropper.py
SqrtS/Widgets/FrameBox.py
SqrtS/Widgets/Image.py
SqrtS/Widgets/Input.py
SqrtS/Widgets/Label.py
SqrtS/Widgets/ListBox.py
SqrtS/Widgets/MouseClickBoard.py
SqrtS/Widgets/PopupWindow.py
SqrtS/Widgets/ProcessBar.py
SqrtS/Widgets/Text.py
SqrtS/Widgets/WebBrowser.py
SqrtS/Widgets/Widget.py
SqrtS/Widgets/WindowDraggingBoard.py
SqrtS/Widgets/__init__.py
SqrtS/Widgets/×BubbleMessage.py
SqrtS/tools/__init__.py
SqrtS/tools/_json_control.py
SqrtS/tools/font.py
SqrtS/tools/image.py
SqrtS/tools/load_theme.py
SqrtS/tools/timer.py
SqrtS/tools/theme_root/__init__.py
SqrtS/tools/theme_root/theme.zip
SqrtS-0.0.1.dist-info/LICENSE
SqrtS-0.0.1.dist-info/METADATA
SqrtS-0.0.1.dist-info/WHEEL
SqrtS-0.0.1.dist-info/top_level.txt
SqrtS-0.0.1.dist-info/RECORD
